LICENSE
MANIFEST.in
README.rst
setup.py
keypath/__init__.py
keypath.egg-info/PKG-INFO
keypath.egg-info/SOURCES.txt
keypath.egg-info/dependency_links.txt
keypath.egg-info/top_level.txt