Metadata-Version: 1.0
Name: keypath
Version: 0.0.4
Summary: Get/set values at a key path in a dict/object
Home-page: https://github.com/fictorial/keypath
Author: Brian Hammond
Author-email: brian@fictorial.com
License: keypath is released under the BSD license:
